pmkoalas/__init__.py
pmkoalas/_logging.py
pmkoalas/complex.py
pmkoalas/directly.py
pmkoalas/dtlog.py
pmkoalas/eventlog.py
pmkoalas/export.py
pmkoalas/read.py
pmkoalas/simple.py
pmkoalas/work.py
pmkoalas/xes.py
pmkoalas/xes_export.py
pmkoalas/_struct/__init__.py
pmkoalas/_struct/collections.py
pmkoalas/conformance/__init__.py
pmkoalas/conformance/dataaware.py
pmkoalas/conformance/matching.py
pmkoalas/conformance/tokenreplay.py
pmkoalas/discovery/__init__.py
pmkoalas/discovery/agrawal_miner.py
pmkoalas/discovery/alpha_miner.py
pmkoalas/discovery/meta.py
pmkoalas/models/__init__.py
pmkoalas/models/dotutil.py
pmkoalas/models/pnfrag.py
pmkoalas/models/transitiontree.py
pmkoalas/models/petrinets/__init__.py
pmkoalas/models/petrinets/dot.py
pmkoalas/models/petrinets/dpn.py
pmkoalas/models/petrinets/export.py
pmkoalas/models/petrinets/guards.py
pmkoalas/models/petrinets/pn.py
pmkoalas/models/petrinets/read.py
pmkoalas/models/petrinets/utils.py
pmkoalas/models/petrinets/wpn.py
pmkoalas-0.4.0.dist-info/LICENSE
pmkoalas-0.4.0.dist-info/METADATA
pmkoalas-0.4.0.dist-info/WHEEL
pmkoalas-0.4.0.dist-info/top_level.txt
pmkoalas-0.4.0.dist-info/RECORD
