Metadata-Version: 2.2
Name: pmkoalas
Version: 0.4.0
Summary: A process mining library that focuses on providing pythonic interactions with event logs and languages.
Author: Adam Burke
Author-email: Adam Banham <adam_banham@hotmail.com>
License: MIT License
Project-URL: Homepage, https://github.com/AdamBanham/koalas
Project-URL: Bug Tracker, https://github.com/AdamBanham/koalas/issues
Classifier: Programming Language :: Python :: 3
Classifier: License :: OSI Approved :: MIT License
Classifier: Operating System :: OS Independent
Requires-Python: >=3.9
License-File: LICENSE
Requires-Dist: tqdm
Requires-Dist: joblib>=1.4.2
Requires-Dist: pyparsing
Provides-Extra: dev
Requires-Dist: xmlschema; extra == "dev"
Requires-Dist: coverage; extra == "dev"
